setup.py
django_queries.egg-info/PKG-INFO
django_queries.egg-info/SOURCES.txt
django_queries.egg-info/dependency_links.txt
django_queries.egg-info/top_level.txt
queries/__init__.py
queries/helpers.py
queries/models.py
queries/options.py
queries/sites.py
queries/util.py
queries/validation.py
queries/widgets.py
queries/templatetags/__init__.py
queries/templatetags/admin_modify.py
queries/templatetags/query_list.py
queries/templatetags/querymedia.py
queries/views/__init__.py
queries/views/decorators.py
queries/views/main.py
queries/views/template.py