Metadata-Version: 1.0
Name: django-queries
Version: 0.1
Summary: Generic query interface for django models
Home-page: http://code.google.com/p/django-queries/
Author: Peter Guthy
Author-email: peter@guthy.at
License: BSD
Download-URL: http://code.google.com/p/django-queries/
Platform: UNKNOWN
Classifier: Development Status :: 4 - Beta
Classifier: Environment :: Web Environment
Classifier: Framework :: Django
Classifier: Intended Audience :: Developers
Classifier: License :: OSI Approved :: BSD License
Classifier: Programming Language :: Python
Classifier: Topic :: Database :: Front-Ends
Classifier: Topic :: Software Development :: Libraries :: Python Modules
